hm_wrapper/__init__.py
hm_wrapper/_utils.py
hm_wrapper/radarr.py
hm_wrapper/sonarr.py
hm_wrapper/tests/__init__.py
hm_wrapper/tests/test__utils.py
hm_wrapper-0.12.3.dist-info/LICENSE
hm_wrapper-0.12.3.dist-info/METADATA
hm_wrapper-0.12.3.dist-info/WHEEL
hm_wrapper-0.12.3.dist-info/top_level.txt
hm_wrapper-0.12.3.dist-info/RECORD
